{
  "Login to continue": "కొనసాగించడానికి లాగిన్ అవ్వండి",
  "Quit": "నిష్క్రమించండి",
  "Retry": "మళ్లీ ప్రయత్నించండి",
  "Login UnSuccessful": "లాగిన్ విజయవంతం కాలేదు",
  "Powered by ": "ద్వారా ఆధారితం",
  " Doorstep Banking": "డోర్స్టెప్ బ్యాంకింగ్",
  "Proceed": "కొనసాగండి",
  "I agree to the": "సమ్మతిస్తున్నాను",
  " Terms and conditions": " నిబంధనలు మరియు షరతులు",
  "Login": "ప్రవేశించండి",
  "Logging in...": "లాగిన్ అవుతోంది...",
  "Resend OTP": "OTP ను మళ్ళీ పంపు",
  "Not Registered yet? ": "ఇంకా నమోదు కాలేదా? ",
  "Register": "నమోదు చేయండి",
  "Mobile Number": "మొబైల్ సంఖ్య",
  "Please enter a valid Phone Number!": "దయచేసి చెల్లుబాటు అయ్యే ఫోన్ నంబర్\u200Cను నమోదు చేయండి! ",
  "Please enter only Numbers!": "దయచేసి సంఖ్యలను మాత్రమే నమోదు చేయండి!",
  "Fetching Details for this number...": "ఈ సంఖ్య కోసం వివరాలను పొందడం...",
  "Forgot PIN ?": "పిన్ మర్చిపోయారా ?",
  "Login with another number": "మరొక సంఖ్యతో లాగిన్ అవ్వండి",
  " -OR- ": " -లేదా- ",
  " Login with PIN ": " పిన్\u200Cతో లాగిన్ అవ్వండి ",
  "ifno": "సమాచారం",
  "Couldn't load the terms and conditions, please retry": "నిబంధనలు మరియు షరతులను లోడ్ చేయలేకపోయాము, దయచేసి మళ్లీ ప్రయత్నించండి",
  "Number of remaining attempts:": "మిగిలిన ప్రయత్నాల సంఖ్య:",
  "Did not receive OTP?": "OTP అందుకోలేదు?",
  "Wait": "OTP కోసం వేచి ఉండండి",
  "ACCEPT TERMS": "నిబంధనలను అంగీకరించండి",
  "In order to sign-in to your account,you need to agree the updated Terms and Condition.": "మీ ఖాతాకు సైన్-ఇన్ చేయడానికి, మీరు నవీకరించిన నిబంధనలు మరియు షరతులను అంగీకరించాలి.",
  "Updating Terms...": "నిబంధనలను నవీకరిస్తోంది...",
  "SUCCESS": "విజయం",
  "SUBMIT": "సమర్పించండి",
  "OK": "అలాగే",
  "BACK": "తిరిగి",
  "ERROR": "లోపం",
  "Please Enter 6 digits OTP": "దయచేసి 6 అంకెలు OTP ని నమోదు చేయండి",
  "Enter OTP": "OTP ని నమోదు చేయండి",
  "       PIN": "       పిన్",
  "Get OTP": "OTP పొందండి",
  "Not Registered yet?": "ఇంకా నమోదు కాలేదా?",
  "  We've sent an OTP to": "  మేము దీనికి OTP పంపాము",
  "Generating OTP... Please wait...": "OTP ని సృష్టిస్తోంది ... దయచేసి వేచి ఉండండి...",
  " Login with OTP ": " OTP తో లాగిన్ అవ్వండి ",
  "Signing in...": "లోనికి ప్రవేశించు...",
  "Please enter a 6 digit pin!": "దయచేసి 6 అంకెల పిన్ను నమోదు చేయండి!",
  "Please Enter only Numbers!": "దయచేసి సంఖ్యలను మాత్రమే నమోదు చేయండి!",




  "Registration!": "నమోదు!",
  "Cancel Registration?": "నమోదును రద్దు చేయండి?",
  "Do you want to cancel Registration, the data entered will not be saved": "మీరు నమోదును రద్దు చేయాలనుకుంటున్నారా, నమోదు చేసిన డేటా సేవ్ చేయబడదు",
  "No": "లేదు",
  "Yes": "అవును",
  " We've sent an OTP to": " మేము దీనికి OTP పంపాము",
  "Registration :": "నమోదు :",
  "Select a security question": "ఒక భద్రతా ప్రశ్న ని ఎంచుకోండి",
  "Loading questions dropdown...": "ప్రశ్నలను డ్రాప్డౌన్ లోడ్ చేస్తోంది...",
  "E-Mail (Optional)": "ఇ-మెయిల్ (ఐచ్ఛికం)",
  "Please enter only Alphabets!": "దయచేసి అక్షరాలను మాత్రమే నమోదు చేయండి!",
  "Please provide a name": "దయచేసి పేరు ఇవ్వండి",
  "Name *": "పేరు *",
  "This field cannot be left empty": "ఈ ఫీల్డ్ ఖాళీగా ఉంచబడదు",
  "Security Answer *": "సెక్యూరిటీ జవాబు *",
  "Please provide an address": "దయచేసి చిరునామా ఇవ్వండి",
  "Address": "చిరునామా",
  "Phone Number *": "ఫోను నంబరు *",
  "OTP": "OTP",
  "Please Enter Alternate Phone Number!": "దయచేసి ప్రత్యామ్నాయ ఫోన్ నంబర్\u200Cను నమోదు చేయండి!",
  "Alternate Phone Number(Optional)": "ప్రత్యామ్నాయ ఫోన్ నంబర్ (ఐచ్ఛికం)",
  "Password must be atleast 6 characters!": "పాస్\u200Cవర్డ్ కనీసం 6 అక్షరాలు ఉండాలి!",
  "PIN *":  "పిన్ *",
  "PIN's don't match": "పిన్ సరిపోలలేదు",
  "Confirm PIN *": "పిన్ నిర్ధారించండి *",
  "GET OTP": "OTP పొందండి",
  "Verify OTP": "OTP ని ధృవీకరించండి",
  "Registering...": "నమోదు...",
  "Your Registration was Successful, you may now login using your credentials": "మీ నమోదు విజయవంతమైంది, మీరు ఇప్పుడు మీ ఆధారాలను ఉపయోగించి లాగిన్ అవ్వవచ్చు",


  "Reset PIN ": "పిన్ రీసెట్ చేయండి ",

  "OTP field is mandatory": "OTP ఫీల్డ్ తప్పనిసరి",
  "Please enter 6 digit OTP!": "దయచేసి 6 అంకెల OTP ని నమోదు చేయండి!",
  "Validating OTP...": "OTP ని ధృవీకరిస్తోంది...",
  "New PIN": "క్రొత్త పిన్",
  "New PIN field is mandatory": "క్రొత్త పిన్ ఫీల్డ్ తప్పనిసరి",
  "Please enter 6 digit PIN!": "దయచేసి 6 అంకెల పిన్ను నమోదు చేయండి!",
  "Confirm New PIN": "క్రొత్త పిన్ను నిర్ధారించండి",
  "Confirm New PIN field is mandatory": "క్రొత్త పిన్ ఫీల్డ్ తప్పనిసరి అని నిర్ధారించండి",
  "Validation": "ధ్రువీకరణ",
  "New PIN and Confirm PIN must be same": "క్రొత్త పిన్ మరియు కన్ఫర్మ్ పిన్ ఒకేలా ఉండాలి",
  "PIN and Confirm PIN must be same": "పిన్ మరియు కన్ఫర్మ్ పిన్ ఒకేలా ఉండాలి",
  "Changing PIN...": "పిన్ మార్చడం...",
  "Change PIN": "పిన్ మార్చండి",
  "Error in Change PIN": "మార్పు పిన్\u200Cలో లోపం",

  "HomePage": "హోమ్\u200Cపేజీ",

  "System": "సిస్టమ్",
  "Service": "సేవ",
  "Others": "ఇతరులు",
  "Help and support": "సహాయం మరియు మద్దతు",
  "View frequently asked questions": "తరచుగా అడిగే ప్రశ్నలను చూడండి",
  "DOWNLOAD": "డౌన్\u200Cలోడ్",
  "View lodged grievances": "దాఖలు చేసిన ఫిర్యాదులను చూడండి",
  "Lodge grievance": "లాడ్జ్ ఫిర్యాదు",
  "About Application": "అప్లికేషన్ గురించి",
  "Name": "పేరు",
  "Phone number": "ఫోను నంబరు",
  "Alt phone number": "ఆల్ట్ ఫోన్ నంబర్",
  "Email": "ఇమెయిల్",
  "Manage Address": "చిరునామాను నిర్వహించండి",
  "Account": "ఖాతా",
  "Manage Saved Accounts": "సేవ్ చేసిన ఖాతాలను నిర్వహించండి",
  "Change PIN   ": "పిన్ మార్చండి",
  "DEACTIVATE": "నిష్క్రియాత్మకం",
  "Do you want to Deactivate account": "మీరు ఖాతాను నిష్క్రియం చేయాలనుకుంటున్నారా",
  "You won't be able to login with this account in future, however you may reactivate this account to continue with our services": "భవిష్యత్తులో మీరు ఈ ఖాతాతో లాగిన్ అవ్వలేరు, అయినప్పటికీ మీరు మా సేవలతో కొనసాగడానికి ఈ ఖాతాను తిరిగి సక్రియం చేయవచ్చు",
  "Cancel": "రద్దు చేయండి",
  "Generating OTP for Deactivation...": "క్రియారహితం కోసం OTP ను ఉత్పత్తి చేస్తోంది...",
  "    Home": "    హోమ్",
  "My services": "నా సేవలు",
  "  Support": "  మద్దతు",
  "   Profile": "   ప్రొఫైల్",
  "Take a picture": "ఫోటో తీ",
  "Select from gallery": "గ్యాలరీ నుండి ఎంచుకోండి",
  "Do you want to Logout from account": "మీరు ఖాతా నుండి లాగ్ అవుట్ చేయాలనుకుంటున్నారా",
  "We'd hate to see you leave...": "మీరు వెళ్ళిపోవడాన్ని మేము ద్వేషిస్తాము ...",
  "Logging Out": "లాగ్ అవుట్",
  "Logout Error": "లాగ్ అవుట్ లోపం",
  "Logout": "లాగ్ అవుట్",

  "YES": "అవును",
  "NO": "లేదు",

  "Current PIN": "ప్రస్తుత పిన్",
  "Old PIN field is mandatory": "పాత పిన్ ఫీల్డ్ తప్పనిసరి",
  "Please Enter a different PIN": "దయచేసి వేరే పిన్ను నమోదు చేయండి",
  "Reset PIN": "పిన్ రీసెట్ చేయండి",

  "Booking Id:   ": "బుకింగ్ ఐడి:   ",
  "Status: ": "స్థితి: ",
  "DONE": "పూర్తి",

  "Booking": "బుకింగ్",
  "Please wait...!": "దయచేసి వేచి ఉండండి...!",
  "Booking details": "బుకింగ్ వివరాలు",
  "Booking Status": "బుకింగ్ స్థితి",
  "Agent Photo": "ఏజెంట్ ఫోటో",
  "CALL": "కాల్ చేయండి",
  "  Service booking details": "  సర్వీస్ బుకింగ్ వివరాలు",
  "View details": "వివరాలను చూడండి",
  "Service Name": "సేవ పేరు",
  "Booking Id": "బుకింగ్ ఐడి",
  "Account Number": "ఖాతా సంఖ్య",
  "Bank Name": "బ్యాంక్ పేరు",
  "AuthCode": "ఆఉథ్చొదె",
  " show": " చూపించు",
  "Status": "స్థితి",
  "    Preferred Date": "    ఇష్టపడే తేదీ",
  "    Preferred Time": "    ఇష్టపడే సమయం",
  "    Cancellation Charge": "    రద్దు ఛార్జ్",
  "    Rs": "    రూ",
  "    Service Charge": "    సేవా ఛార్జ్",
  "    Branch Name": "    శాఖ పేరు",
  "    Requested Date": "    అభ్యర్థించిన తేదీ",
  "  Additional Service details":   "  అదనపు సేవా వివరాలు",
  "  Agent details": "  ఏజెంట్ వివరాలు",
  "Mobile": "మొబైల్",
  "ID": "ఐడి",
  "  Debit details": "  డెబిట్ వివరాలు",
  "Bank Reference Number": "బ్యాంక్ రిఫరెన్స్ నంబర్",
  "Debit Status": "డెబిట్ స్థితి",
  "Lodge Grievance": "లాడ్జ్ గ్రీవెన్స్",
  "Cancel Service": "సేవను రద్దు చేయండి",
  "The length of bank list was 0": "బ్యాంక్ జాబితా యొక్క పొడవు 0",
  "Select your bank": "మీ బ్యాంకును ఎంచుకోండి",
  "Book From Saved Account": "సేవ్ చేసిన ఖాతా నుండి బుక్ చేయండి",
  "Choose an Address": "చిరునామాను ఎంచుకోండి",
  "Add this Address": "ఈ చిరునామాను జోడించండి",
  "Get Current Location": "ప్రస్తుత స్థానాన్ని పొందండి",

  "Grievances": "గ్రీవెన్స్",
  "Grievance ID :": "గ్రీవెన్స్ ఐడి :",
  "Created on :": "న సృష్టించబడింది :",
  "Status :": "స్థితి :",
  "Message: ": "సందేశం: ",
  "Request Account Statement": "ఖాతా స్టేట్మెంట్ అభ్యర్థించండి",
  "CANCEL": "రద్దు చేయండి",
  "PROCEED": "కొనసాగండి",

  "Add Address": "చిరునామాను జోడించండి",
  "  Loading...": "  లోడ్ చేస్తోంది...",
  "Search  ": "వెతకండి  ",
  "Please fill the details": "దయచేసి వివరాలను పూరించండి",
  "Adding Address": "చిరునామాను కలుపుతోంది",
  "Address Added Successfully": "చిరునామా విజయవంతంగా జోడించబడింది",
  "State *": "రాష్ట్రం *",
  "Pincode *": "పిన్ కోడ్ *",
  "LandMark *": "ల్యాండ్\u200Cమార్క్ *",
  "City *": "నగరం *",
  "House / Flat Number *": "ఇల్లు / ఫ్లాట్ సంఖ్య *",
  "Delivery instruction (Optional)": "డెలివరీ ఇన్స్ట్రక్షన్ (ఐచ్ఛికం)",
  "Home": "ఇల్లు",
  "Office": "కార్యాలయం",
  "Other": "ఇతర",

  "Saved Accounts": "ఖాతాలను సేవ్ చేసారు",
  "Delete Account": "ఖాతాను తొలగించండి",
  "Are you sure you want to delete this from your Saved Accounts": "మీరు మీ సేవ్ చేసిన ఖాతాల నుండి దీన్ని తొలగించాలనుకుంటున్నారా?",
  "Delete": "తొలగించు",


  "Manage Addresses": "చిరునామాలను నిర్వహించండి",
  "Address (Home)": "చిరునామా (ఇల్లు)",
  "House No : ": "హౌస్ సంఖ్య : ",
  "LANDMARK :": "లాండ్\u200Cమార్క్ :",
  "PINCODE :": "పిన్ కోడ్ :",
  "Update Address?": "చిరునామాను నవీకరించండి?",
  "Are you sure you want to edit this address": "మీరు ఖచ్చితంగా ఈ చిరునామాను సవరించాలనుకుంటున్నారా",
  "Update": "నవీకరణ",
  "Update Address":"చిరునామాను నవీకరించండి",
  "Delete Address": "చిరునామాను తొలగించండి",
  "Are you sure you want to delete address": "మీరు ఖచ్చితంగా చిరునామాను తొలగించాలనుకుంటున్నారా?",
  "Deleting Address": "చిరునామాను తొలగిస్తోంది",

  "Cancel Serivce": "సేవను రద్దు చేయండి",
  "Back": "తిరిగి",
  "Cancelling Service": "సేవను రద్దు చేస్తోంది",
  "Lodging Grievance": "ఫిర్యాదు లాడ్జింగ్",
  "Loading Cancellation Reasons...": "రద్దు కారణాలను లోడ్ చేస్తోంది...",
  "The service name is": "సేవ పేరు",

  "Give Your Feedback": "మీ అభిప్రాయాన్ని ఇవ్వండి",
  "Share your experience of last completed service":"చివరిగా పూర్తి చేసిన సేవ యొక్క మీ అనుభవాన్ని పంచుకోండి",
  " Booking ID :": " బుకింగ్ ఐడి :",
  " Bank :": " బ్యాంక్ :",
  " Service :": " సేవ :",
  "Rating(Mandatory)": "రేటింగ్ (తప్పనిసరి)",
  "Remarks(Optional)": "వ్యాఖ్యలు (ఐచ్ఛికం)",
  "Submit": "సమర్పించండి",

  "Feedback List": "అభిప్రాయ జాబితా",
  "Booking ID": "బుకింగ్ ఐడి",
  "Bank": "బ్యాంక్",

  "Update this Address": "ఈ చిరునామాను నవీకరించండి",

  "Deactivate Account": "ఖాతాను నిష్క్రియం చేయండి",

  "Alert": "హెచ్చరిక",
  "Please enter the valid From date": "తేదీ నుండి చెల్లుబాటు అయ్యేదాన్ని నమోదు చేయండి",
  "Please enter the valid To date": "దయచేసి చెల్లుబాటు అయ్యే తేదీని నమోదు చేయండి",
  "Please enter the valid date range": "దయచేసి చెల్లుబాటు అయ్యే తేదీ పరిధిని నమోదు చేయండి",


  "Please Enter valid data!": "దయచేసి చెల్లుబాటు అయ్యే డేటాను నమోదు చేయండి!",
  "Enter value less than": "తక్కువ విలువను నమోదు చేయండి",
  "Enter value more than": "ఎక్కువ విలువను నమోదు చేయండి",

  "Select": "ఎంచుకోండి",
  "Loading Grievance Dropdown...": "గ్రీవెన్స్ డ్రాప్\u200Cడౌన్ లోడ్ అవుతోంది...",
  "Remarks": "వ్యాఖ్యలు",
  "Remarks cannot be empty": "వ్యాఖ్యలు ఖాళీగా ఉండకూడదు",
  "Your grievance was lodged successfully with the id": "మీ ఫిర్యాదు ఐడితో విజయవంతంగా దాఖలైంది",
  "Select security question": "భద్రతా ప్రశ్నను ఎంచుకోండి",
  "Select Type": "రకం ఎంచుకోండి",
  "Select reason": "కారణం ఎంచుకోండి",

  "Grievance for": "గ్రీవెన్స్ కోసం",

  "Select cancel reason": "క్యాన్సర్ కారణాన్ని ఎంచుకోండి",
  " Rs": " రూ",
  "Reason:": "కారణం:",

  "DoorstepBanking": "డోర్స్టెప్బ్యాంకింగ్",
  "Powered by Integra Micro Systems (P) Ltd.": "ఇంటిగ్రే మైక్రో సిస్టమ్స్ (పి) లిమిటెడ్ చేత ఆధారితం.",
  "Doorstep banking is facility provided to you so that you don't have to visit your bank branch for your routine banking activities like cash deposit cash withdrawal, cheque deposit or making a demand draft.":"డోర్స్టెప్ బ్యాంకింగ్ సదుపాయం మీకు అందించబడింది మరియు నగదు డిపాజిట్ నగదు ఉపసంహరణ, చెక్ డిపాజిట్ లేదా డిమాండ్ డ్రాఫ్ట్ చేయడం వంటి మీ సాధారణ బ్యాంకింగ్ కార్యకలాపాలతో మీరు దీన్ని చేయవచ్చు.",
  "Version:": "వెరిజోన్:",


  "Book Service": "బుకింగ్ సేవ",
  "Cancel Booking?": "బుకింగ్ రద్దు చేయాలా?",
  "Are you sure you want to cancel your Booking?": "మీరు ఖచ్చితంగా మీ బుకింగ్\u200Cను రద్దు చేయాలనుకుంటున్నారా?",
  "Please wait while we confirm your Request": "మేము మీ అభ్యర్థనను ధృవీకరించేటప్పుడు వేచి ఉండండి",
  "An OTP has been sent to": "ఒక OTP పంపబడింది",
  "Retries Left": "మళ్లీ  తిరిగి ప్రయత్నించండి",
  "Select your account": "మీ ఖాతాను ఎంచుకోండి",
  "Save this Account for future Booking": "భవిష్యత్ బుకింగ్ కోసం ఈ ఖాతాను సేవ్ చేయండి",
  "Please wait....": " దయచేసి వేచి ఉండండి....",
  "Please select the your account": "దయచేసి మీ ఖాతాను ఎంచుకోండి",
  "Service Charge : Rs": "సేవా ఛార్జ్ : రూ",
  "Confirm booking": "బుకింగ్ నిర్ధారించండి",
  "Name : ": "పేరు : ",
  "Service Type : ": "సేవా రకం : ",
  "Bank : ": "బ్యాంక్ : ",
  "Branch : ": "బ్రాంచ్ : ",
  "Address : ": "చిరునామా : ",
  "Account Number : ": "ఖాతా సంఖ్య : ",
  "Cancellation Charge : Rs": "రద్దు ఛార్జ్ : రూ",
  "Preferred Time : ": "ఇష్టపడే సమయం : ",
  "Amount of Rs.": "మొత్తం రూ.",
  " will be deducted from account no.": " ఖాతా సంఖ్య నుండి తీసివేయబడుతుంది.",
  " +GST will be deducted from account no.": " +GST ఖాతా సంఖ్య నుండి తీసివేయబడుతుంది.",
  "Please wait while we confirm your Booking": "మేము మీ బుకింగ్\u200Cను ధృవీకరించేటప్పుడు వేచి ఉండండి",
  " Booking Successful": " బుకింగ్ విజయవంతమైంది",
  "Booking ID : ": "బుకింగ్ ఐడి : ",
  "Confirm": "నిర్ధారించండి",
  "Financial": "ఆర్థిక",
  "Non-Financial": "ఆర్థికేతర",
  "Select Service": "సేవను ఎంచుకోండి",
  "Choose an address": "చిరునామాను ఎంచుకోండి",
  "(+new)": "(+క్రొత్తది)",
  "No branch found": "శాఖ ఏదీ కనుగొనబడలేదు",
  "Select your preferred branch": "మీకు ఇష్టమైన శాఖను ఎంచుకోండి",
  "Pick your time": "మీ సమయాన్ని ఎంచుకోండి",

  "Language": "భాష",

  "Reactivate Account ": "ఖాతాను తిరిగి సక్రియం చేయండి",
  "Reactivate!":"తిరిగి సక్రియం చేయండి!",
  "Reactivate":"తిరిగి సక్రియం చేయండి",
  "Your reactivation was successful, you may now login using your credentials": "మీ క్రియాశీలత విజయవంతమైంది, మీరు ఇప్పుడు మీ ఆధారాలను ఉపయోగించి లాగిన్ అవ్వవచ్చు",
  "Verifying OTP":"OTP ని ధృవీకరిస్తోంది",
  "Validating and deactivating...": "ధృవీకరించడం మరియు నిష్క్రియం చేయడం ...",

  "The app will now quit": "అప్పీలికేషన్ ఇప్పుడు నిష్క్రమిస్తుంది",

  "Unable to change the Pincode":"పిన్\u200Cకోడ్\u200Cను మార్చడం సాధ్యం కాలేదు",

  "Please enter the authCode...!":"దయచేసి ప్రామాణీకరణ కోడ్‌ను నమోదు చేయండి ...!",

  "Pincode must be within same city": "\nపిన్\u200Cకోడ్ ఒకే నగరంలో ఉండాలి",

  "User already exists": "వినియోగదారు ఉన్నారు",

  "Complaint Details": "ఫిర్యాదు వివరాలు",
  "Complaint Id: ": "ఫిర్యాదు ఐడి: ",
  "Complaint Status: ": "ఫిర్యాదు స్థితి: ",
  "CreatedDate: ": "సృష్టించిన తేదీ: ",
  "Grievance Type: ": "గ్రీవెన్స్ టైప్: ",
  "Reason: ": "కారణం: ",
  "Reason": "కారణం",
  "Remarks: ": "వ్యాఖ్యలు: ",
  "Service BookingID: ": "సర్వీస్ బుకింగ్ ఐడి: ",

  "Your grievance was lodged successfully.":"మీ ఫిర్యాదు విజయవంతంగా దాఖలైంది",

  "(You must have an account with the bank)":"(మీకు బ్యాంకులో ఖాతా ఉండాలి)",

  "Edit Pincode": "పిన్కోడ్ మార్చండి",

  "Facing Issue? Click Here": "సమస్యలను ఎదుర్కొంటున్నారా? ఇక్కడ క్లిక్ చేయండి",

  "Resend OTP Status":"తిరిగి పంపిన OTP స్థితి",

  "Next": "తరువాత",
  "Change Language": "భాష మార్చు",

  "Language Selection":"భాషా ఎంపిక",

  "PSB Alliance is an umbrella setup of all Public Sector Banks, jointly offering important customer oriented services envisaged by Govt. of India under EASE of Banking reforms.\\nDoor Step Banking is one such initiative taken by PSB Alliance through which customers can avail major Banking transaction services at their Door Step. It is being implemented with help of Door Step Banking (DSB) agents in 40 major Centers across the Country for offering different financial as well as non financial banking services.\\nPSB Alliance comprising 12 Public Sector Banks being anchored by UCO Bank, have engaged  M/s Integra Microsystems (P) Ltd to provide “Door Step Banking through Universal Touch Points” facility to customer(s) of 12 PSBs Banks in 60 & 40 Specified Centres respectively as mentioned in (List of centers) within the norms stipulated by PSB Alliance.": "పిఎస్బి అలయన్స్ అన్ని ప్రభుత్వ రంగ బ్యాంకుల గొడుగు సెటప్, ప్రభుత్వం సంకల్పించిన ముఖ్యమైన కస్టమర్ ఆధారిత సేవలను సంయుక్తంగా అందిస్తోంది. బ్యాంకింగ్ సంస్కరణల యొక్క EASE కింద భారతదేశం. PS n డోర్ స్టెప్ బ్యాంకింగ్ అనేది పిఎస్బి అలయన్స్ తీసుకున్న ఒక ప్రయత్నం, దీని ద్వారా వినియోగదారులు వారి డోర్ స్టెప్ వద్ద ప్రధాన బ్యాంకింగ్ లావాదేవీ సేవలను పొందవచ్చు. వివిధ ఆర్థిక మరియు ఆర్థికేతర బ్యాంకింగ్ సేవలను అందించడానికి దేశవ్యాప్తంగా 40 ప్రధాన కేంద్రాల్లోని డోర్ స్టెప్ బ్యాంకింగ్ (డిఎస్బి) ఏజెంట్ల సహాయంతో ఇది అమలు చేయబడుతోంది. / s ఇంటిగ్రే మైక్రోసిస్టమ్స్ (పి) లిమిటెడ్ పిఎస్\u200Cబి నిర్దేశించిన నిబంధనల ప్రకారం (కేంద్రాల జాబితా) లో పేర్కొన్న విధంగా వరుసగా 60 మరియు 40 నిర్దేశిత కేంద్రాల్లోని 12 పిఎస్\u200Cబి బ్యాంకుల కస్టమర్ (ల) కు “యూనివర్సల్ టచ్ పాయింట్స్ ద్వారా డోర్ స్టెప్ బ్యాంకింగ్” సౌకర్యాన్ని అందించడానికి. కూటమి."
}